paynexus/Colors.py
paynexus/__init__.py
paynexus/main.py
PayNexus-0.2.5.dist-info/LICENSE
PayNexus-0.2.5.dist-info/METADATA
PayNexus-0.2.5.dist-info/WHEEL
PayNexus-0.2.5.dist-info/top_level.txt
PayNexus-0.2.5.dist-info/RECORD
