Metadata-Version: 2.1
Name: PayNexus
Version: 0.2.5
Summary: PayNexus: PythonからPayPayを操作できる非公式モジュールです。
Home-page: https://github.com/harumaki4649/PayNexus
Download-URL: https://github.com/harumaki4649/PayNexus
Author: tp-link
Author-email: support@disnana.com
Maintainer: tp-link
Maintainer-email: support@disnana.com
License: BSD 3-Clause
Classifier: Intended Audience :: Science/Research
Classifier: License :: OSI Approved :: BSD License
Classifier: Programming Language :: Python :: 3
Classifier: Programming Language :: Python :: 3.6
Classifier: Programming Language :: Python :: 3.7
Classifier: Programming Language :: Python :: 3.8
Classifier: Programming Language :: Python :: 3.9
Classifier: Programming Language :: Python :: 3 :: Only
Classifier: Topic :: Scientific/Engineering
Classifier: Topic :: Scientific/Engineering :: Visualization
Classifier: Topic :: Scientific/Engineering :: Artificial Intelligence
Classifier: Topic :: Multimedia :: Graphics
Classifier: Framework :: Matplotlib
Requires-Python: >=3.9
License-File: LICENSE
Requires-Dist: cryptography ==42.0.5
Requires-Dist: discord-webhook ==1.3.1
Requires-Dist: Requests ==2.31.0
Requires-Dist: term-printer ==1.1
Requires-Dist: typing-extensions ==4.11.0
